<?xml version="1.0" encoding="utf-8" ?>
<dwsync>
<file name="index.php" server="Mac/Applications/MAMP/htdocs/Tyndall-IFS/" local="3611813654" remote="3611813654" Dst="-1" />
<file name="closedhand.cur" server="Mac/Applications/MAMP/htdocs/Tyndall-IFS/" local="3612424614" remote="3612424614" Dst="-1" />
<file name="layers.css" server="Mac/Applications/MAMP/htdocs/Tyndall-IFS/" local="3611813656" remote="3611813656" Dst="-1" />
<file name="liquideffect.css" server="Mac/Applications/MAMP/htdocs/Tyndall-IFS/" local="3611126374" remote="3611126374" Dst="-1" />
<file name="settings.css" server="Mac/Applications/MAMP/htdocs/Tyndall-IFS/" local="3612424614" remote="3612424614" Dst="-1" />
<file name="settings-ver.5.2.3.css" server="Mac/Applications/MAMP/htdocs/Tyndall-IFS/" local="3538371712" remote="3538371712" Dst="-1" />
<file name="openhand.cur" server="Mac/Applications/MAMP/htdocs/Tyndall-IFS/" local="3612424614" remote="3612424614" Dst="-1" />
<file name="tp-color-picker.css" server="Mac/Applications/MAMP/htdocs/Tyndall-IFS/" local="3611813656" remote="3611813656" Dst="-1" />
<file name="navigation.css" server="Mac/Applications/MAMP/htdocs/Tyndall-IFS/" local="3611813656" remote="3611813656" Dst="-1" />
<file name="settings-source.css" server="Mac/Applications/MAMP/htdocs/Tyndall-IFS/" local="3611813656" remote="3611813656" Dst="-1" />
<file name="closedhand.cur" server="C:/wamp64/www/Tyndall-IFS/" local="131740534140000000" remote="131740570140000000" Dst="1" />
<file name="index.php" server="C:/wamp64/www/Tyndall-IFS/" local="131734424540000000" remote="131734460540000000" Dst="1" />
<file name="layers.css" server="C:/wamp64/www/Tyndall-IFS/" local="131734424560000000" remote="131734460560000000" Dst="1" />
<file name="liquideffect.css" server="C:/wamp64/www/Tyndall-IFS/" local="131727551740000000" remote="131727587740000000" Dst="1" />
<file name="navigation.css" server="C:/wamp64/www/Tyndall-IFS/" local="131734424560000000" remote="131734460560000000" Dst="1" />
<file name="openhand.cur" server="C:/wamp64/www/Tyndall-IFS/" local="131740534140000000" remote="131740570140000000" Dst="1" />
<file name="settings-source.css" server="C:/wamp64/www/Tyndall-IFS/" local="131734424560000000" remote="131734460560000000" Dst="1" />
<file name="settings-ver.5.2.3.css" server="C:/wamp64/www/Tyndall-IFS/" local="131000005120000000" remote="131000005120000000" Dst="1" />
<file name="settings.css" server="C:/wamp64/www/Tyndall-IFS/" local="131740534140000000" remote="131740570140000000" Dst="1" />
<file name="tp-color-picker.css" server="C:/wamp64/www/Tyndall-IFS/" local="131734424560000000" remote="131734460560000000" Dst="1" />
</dwsync>